n2dit/__init__.py
n2dit/__main__.py
n2dit/controller.py
n2dit/cycle_gan_model.py
n2dit/dataset_loader.py
n2dit/imagepool.py
n2dit/logger.py
n2dit/model_manager.py
n2dit/networks.py
n2dit/option_manager.py
n2dit/reporter.py
n2dit/version.py
n2dit/vgg19.py
tests/__init__.py
tests/test_controller.py
n2dit-1.0.0.dist-info/LICENSE
n2dit-1.0.0.dist-info/METADATA
n2dit-1.0.0.dist-info/WHEEL
n2dit-1.0.0.dist-info/entry_points.txt
n2dit-1.0.0.dist-info/top_level.txt
n2dit-1.0.0.dist-info/RECORD
