Metadata-Version: 2.1
Name: n2dit
Version: 1.0.0
Summary: Deep learning-based Night-to-Day image-translation software
Home-page: https://gitlab.com/deeva/Night-to-Day-Image-translation
Author: The Deeva Authors
License: MIT
Platform: UNKNOWN
Classifier: Programming Language :: Python :: 3
Classifier: License :: OSI Approved :: MIT License
Classifier: Operating System :: OS Independent
Requires-Python: >=3.6
Requires-Dist: gast (==0.2.2)
Requires-Dist: numpy (==1.16.2)
Requires-Dist: tensorflow-gpu (==1.14)
Requires-Dist: matplotlib (==3.1.1)
Requires-Dist: pillow (==6.2.1)
Requires-Dist: opencv-python (==3.4.2.17)
